[
  {
    "id": "joongna",
    "name": "Joongna",
    "region": "korea",
    "regionName": "Hàn Quốc",
    "regionFlag": "🇰🇷",
    "currency": "KRW",
    "status": "success",
    "count": 294,
    "error": "",
    "dataFile": "data/joongna.json",
    "crawl": {
      "keyword": "NovaTouch",
      "keywords": [
        "NovaTouch",
        "realforce",
        "리얼포스 R2",
        "realforce 87",
        "realforce 101",
        "topre",
        "leopold fC660",
        "rule",
        "Cooler Master"
      ],
      "sort": "newest",
      "limit": 50,
      "crawledAt": "2026-06-26T00:13:47.467Z"
    }
  },
  {
    "id": "bunjang",
    "name": "Bunjang",
    "region": "korea",
    "regionName": "Hàn Quốc",
    "regionFlag": "🇰🇷",
    "currency": "KRW",
    "status": "success",
    "count": 397,
    "error": "",
    "dataFile": "data/bunjang.json",
    "crawl": {
      "keyword": "NovaTouch",
      "keywords": [
        "NovaTouch",
        "realforce",
        "realforce 101",
        "realforce 87",
        "realforce 86",
        "리얼포스 R2",
        "660c",
        "leopold fC660",
        "topre",
        "rule",
        "Cooler Master",
        "NovaTouch TKL"
      ],
      "sort": "newest",
      "limit": 50,
      "crawledAt": "2026-06-26T00:13:47.467Z"
    }
  },
  {
    "id": "guheyo",
    "name": "Guheyo",
    "region": "korea",
    "regionName": "Hàn Quốc",
    "regionFlag": "🇰🇷",
    "currency": "KRW",
    "status": "success",
    "count": 48,
    "error": "",
    "dataFile": "data/guheyo.json",
    "crawl": {
      "keyword": "NovaTouch",
      "keywords": [
        "NovaTouch",
        "realforce",
        "rule"
      ],
      "sort": "newest",
      "limit": 50,
      "crawledAt": "2026-06-26T00:13:47.467Z"
    }
  },
  {
    "id": "mercari",
    "name": "Mercari",
    "region": "japan",
    "regionName": "Nhật Bản",
    "regionFlag": "🇯🇵",
    "currency": "JPY",
    "status": "success",
    "count": 452,
    "error": "",
    "dataFile": "data/mercari.json",
    "crawl": {
      "keyword": "NovaTouch",
      "keywords": [
        "NovaTouch",
        "realforce",
        "topre",
        "660c",
        "leopold fC660",
        "realforce 101",
        "rule",
        "Cooler Master"
      ],
      "sort": "newest",
      "limit": 50,
      "crawledAt": "2026-06-26T00:13:47.467Z"
    }
  }
]
